tests/__init__.py
tests/test_ast_nodes.py
tests/test_evaluator.py
tests/test_model.py
tests/test_parser.py
tests/test_reader.py
tests/test_tokenizer.py
tests/test_xltypes.py
tests/testing.py
tests/resources/ABS.xlsx
tests/resources/ACOS.xlsx
tests/resources/ASIN.xlsx
tests/resources/ATAN.xlsx
tests/resources/ATAN2.xlsx
tests/resources/AVERAGE.xlsx
tests/resources/CEILING.xlsx
tests/resources/CHOOSE.xlsx
tests/resources/CONCAT.xlsx
tests/resources/CONCATENATE.xlsx
tests/resources/COS.xlsx
tests/resources/COSH.xlsx
tests/resources/COUNT.xlsx
tests/resources/COUNTA.xlsx
tests/resources/COUNTIF.xlsx
tests/resources/COUNTIFS.xlsx
tests/resources/DATE.xlsx
tests/resources/DATEDIF.xlsx
tests/resources/DAY.xlsx
tests/resources/DAYS.xlsx
tests/resources/EDATE.xlsx
tests/resources/EOMONTH.xlsx
tests/resources/EXACT.xlsx
tests/resources/FIND.xlsx
tests/resources/INFORMATION.xlsx
tests/resources/INT.xlsx
tests/resources/IRR.xlsx
tests/resources/LEN.xlsx
tests/resources/LN.xlsx
tests/resources/MATCH.xlsx
tests/resources/MAX.xlsx
tests/resources/MID.xlsx
tests/resources/MIN.xlsx
tests/resources/MOD.xlsx
tests/resources/MONTH.xlsx
tests/resources/NPV.xlsx
tests/resources/PMT.xlsx
tests/resources/POWER.xlsx
tests/resources/RIGHT.xlsx
tests/resources/ROUND.xlsx
tests/resources/ROUNDDOWN.xlsx
tests/resources/ROUNDUP.xlsx
tests/resources/SLN.xlsx
tests/resources/SQRT.xlsx
tests/resources/SUM.xlsx
tests/resources/SUMIFS.xlsx
tests/resources/SUMPRODUCT.xlsx
tests/resources/VDB.xlsx
tests/resources/VLOOKUP.xlsx
tests/resources/XNPV.xlsx
tests/resources/YEAR.xlsx
tests/resources/YEARFRAC.xlsx
tests/resources/addition.xlsx
tests/resources/defined_names.xlsx
tests/resources/division.xlsx
tests/resources/double_minus.xlsx
tests/resources/logical.xlsx
tests/resources/model.json
tests/resources/model_compiler_and_evaluate.xlsx
tests/resources/multiplication.xlsx
tests/resources/reader.json
tests/resources/reader.xlsm
tests/resources/subtraction.xlsx
tests/xlfunctions/__init__.py
xlcalculator-0.2.13.dist-info/LICENSE
xlcalculator-0.2.13.dist-info/METADATA
xlcalculator-0.2.13.dist-info/WHEEL
xlcalculator-0.2.13.dist-info/top_level.txt
xlcalculator-0.2.13.dist-info/RECORD
