Metadata-Version: 2.1
Name: xlcalculator
Version: 0.2.13
Summary: Converts MS Excel formulas to Python and evaluates them.
Home-page: https://github.com/bradbase/xlcalculator
Author: Bradley van Ree
Author-email: brads@bradbase.net
License: MIT
Keywords: xls,Excel,spreadsheet,workbook,data analysis,analysisreading excel,excel formula,excel formulas,excel equations,excel equation,formula,formulas,equation,equations,timeseries,time series,research,scenario analysis,scenario,modelling,model,unit testing,testing,audit,calculation,evaluation,data science,openpyxl
Platform: UNKNOWN
Classifier: Development Status :: 5 - Production/Stable
Classifier: Intended Audience :: Developers
Classifier: Intended Audience :: Science/Research
Classifier: Intended Audience :: Information Technology
Classifier: Intended Audience :: Financial and Insurance Industry
Classifier: License :: OSI Approved :: MIT License
Classifier: Natural Language :: English
Classifier: Operating System :: OS Independent
Classifier: Programming Language :: Python :: 3
Classifier: Programming Language :: Python :: 3.7
Classifier: Programming Language :: Python :: 3.8
Classifier: Topic :: Office/Business :: Financial :: Spreadsheet
Classifier: Topic :: Scientific/Engineering
Classifier: Topic :: Scientific/Engineering :: Information Analysis
Classifier: Topic :: Scientific/Engineering :: Mathematics
Classifier: Topic :: Software Development :: Libraries
Classifier: Topic :: Software Development :: Libraries :: Python Modules
Classifier: Topic :: Software Development :: Testing
Classifier: Topic :: Software Development :: Testing :: Unit
Classifier: Topic :: Utilities
Requires-Python: >=3.7
Requires-Dist: jsonpickle
Requires-Dist: numpy
Requires-Dist: pandas
Requires-Dist: openpyxl
Requires-Dist: numpy-financial
Requires-Dist: yearfrac (==0.4.4)
Requires-Dist: mock
Requires-Dist: scipy
Provides-Extra: build
Requires-Dist: pip-tools ; extra == 'build'
Provides-Extra: test
Requires-Dist: coverage ; extra == 'test'
Requires-Dist: flake8 ; extra == 'test'
Requires-Dist: mock ; extra == 'test'
Requires-Dist: pytest ; extra == 'test'
Requires-Dist: pytest-cov ; extra == 'test'
